e8_waveforms/e8.v
module f (
	input logic[11:0] x, 
	input logic[11:0] y, 
	output logic[11:0] a,
	output logic[11:0] b
	); 
	
	logic[23:0] s; 
	
	always @(*) begin 
		s = x + y; 
		a = s[23:12]; 
		b = s[11:0]; 
	end 
	
endmodule

e8_waveforms/e8_waveforms.v
module e8_waveforms(); 

	logic[11:0] x; 
	logic[11:0] y; 
	logic[11:0] a, a_ref;
	logic[11:0] b, b_ref;
	logic[23:0] s; 
	
	initial begin 
		$dumpfile("e8_waveforms.vcd");
		$dumpvars(0, e8_waveforms); 
		x = 0; 
		y = 0; 
		repeat(4096) begin 
			x = y + 1; 
			#1; 
			s = x + y; 
			a_ref = s[23:12]; 
			b_ref = s[11:0]; 
			assert(a == a_ref); 
			assert(b == b_ref); 
			y += 1; 
			#1; 
		end 
	end 
	
	f dut (x, y, a, b); 
endmodule

e8_waveforms/e8_waveforms.vcd
$date
	Fri Nov 12 17:15:51 2021
$end
$version
	Icarus Verilog
$end
$timescale
	1s
$end
$scope module e8_waveforms $end
$var wire 12 ! b [11:0] $end
$var wire 12 " a [11:0] $end
$var reg 12 # a_ref [11:0] $end
$var reg 12 $ b_ref [11:0] $end
$var reg 24 % s [23:0] $end
$var reg 12 & x [11:0] $end
$var reg 12 ' y [11:0] $end
$scope module dut $end
$var wire 12 ( x [11:0] $end
$var wire 12 ) y [11:0] $end
$var reg 12 * a [11:0] $end
$var reg 12 + b [11:0] $end
$var reg 24 , s [23:0] $end
$upscope $end
$upscope $end
$enddefinitions $end
#0
$dumpvars
b1 ,
b1 +
b0 *
b0 )
b1 (
b0 '
b1 &
bx %
bx $
bx #
b0 "
b1 !
$end
#1
b10 !
b10 +
b10 ,
b1 '
b1 )
b1 $
b0 #
b1 %
#2
b11 !
b11 +
b11 ,
b10 &
b10 (
#3
b100 !
b100 +
b100 ,
b10 '
b10 )
b11 $
b11 %
#4
b101 !
b101 +
b101 ,
b11 &
b11 (
#5
b110 !
b110 +
b110 ,
b11 '
b11 )
b101 $
b101 %
#6
b111 !
b111 +
b111 ,
b100 &
b100 (
#7
b1000 !
b1000 +
b1000 ,
b100 '
b100 )
b111 $
b111 %
#8
b1001 !
b1001 +
b1001 ,
b101 &
b101 (
#9
b1010 !
b1010 +
b1010 ,
b101 '
b101 )
b1001 $
b1001 %
#10
b1011 !
b1011 +
b1011 ,
b110 &
b110 (
#11
b1100 !
b1100 +
b1100 ,
b110 '
b110 )
b1011 $
b1011 %
#12
b1101 !
b1101 +
b1101 ,
b111 &
b111 (
#13
b1110 !
b1110 +
b1110 ,
b111 '
b111 )
b1101 $
b1101 %
#14
b1111 !
b1111 +
b1111 ,
b1000 &
b1000 (
#15
b10000 !
b10000 +
b10000 ,
b1000 '
b1000 )
b1111 $
b1111 %
#16
b10001 !
b10001 +
b10001 ,
b1001 &
b1001 (
#17
b10010 !
b10010 +
b10010 ,
b1001 '
b1001 )
b10001 $
b10001 %
#18
b10011 !
b10011 +
b10011 ,
b1010 &
b1010 (
#19
b10100 !
b10100 +
b10100 ,
b1010 '
b1010 )
b10011 $
b10011 %
#20
b10101 !
b10101 +
b10101 ,
b1011 &
b1011 (
#21
b10110 !
b10110 +
b10110 ,
b1011 '
b1011 )
b10101 $
b10101 %
#22
b10111 !
b10111 +
b10111 ,
b1100 &
b1100 (
#23
b11000 !
b11000 +
b11000 ,
b1100 '
b1100 )
b10111 $
b10111 %
#24
b11001 !
b11001 +
b11001 ,
b1101 &
b1101 (
#25
b11010 !
b11010 +
b11010 ,
b1101 '
b1101 )
b11001 $
b11001 %
#26
b11011 !
b11011 +
b11011 ,
b1110 &
b1110 (
#27
b11100 !
b11100 +
b11100 ,
b1110 '
b1110 )
b11011 $
b11011 %
#28
b11101 !
b11101 +
b11101 ,
b1111 &
b1111 (
#29
b11110 !
b11110 +
b11110 ,
b1111 '
b1111 )
b11101 $
b11101 %
#30
b11111 !
b11111 +
b11111 ,
b10000 &
b10000 (
#31
b100000 !
b100000 +
b100000 ,
b10000 '
b10000 )
b11111 $
b11111 %
#32
b100001 !
b100001 +
b100001 ,
b10001 &
b10001 (
#33
b100010 !
b100010 +
b100010 ,
b10001 '
b10001 )
b100001 $
b100001 %
#34
b100011 !
b100011 +
b100011 ,
b10010 &
b10010 (
#35
b100100 !
b100100 +
b100100 ,
b10010 '
b10010 )
b100011 $
b100011 %
#36
b100101 !
b100101 +
b100101 ,
b10011 &
b10011 (
#37
b100110 !
b100110 +
b100110 ,
b10011 '
b10011 )
b100101 $
b100101 %
#38
b100111 !
b100111 +
b100111 ,
b10100 &
b10100 (
#39
b101000 !
b101000 +
b101000 ,
b10100 '
b10100 )
b100111 $
b100111 %
#40
b101001 !
b101001 +
b101001 ,
b10101 &
b10101 (
#41
b101010 !
b101010 +
b101010 ,
b10101 '
b10101 )
b101001 $
b101001 %
#42
b101011 !
b101011 +
b101011 ,
b10110 &
b10110 (
#43
b101100 !
b101100 +
b101100 ,
b10110 '
b10110 )
b101011 $
b101011 %
#44
b101101 !
b101101 +
b101101 ,
b10111 &
b10111 (
#45
b101110 !
b101110 +
b101110 ,
b10111 '
b10111 )
b101101 $
b101101 %
#46
b101111 !
b101111 +
b101111 ,
b11000 &
b11000 (
#47
b110000 !
b110000 +
b110000 ,
b11000 '
b11000 )
b101111 $
b101111 %
#48
b110001 !
b110001 +
b110001 ,
b11001 &
b11001 (
#49
b110010 !
b110010 +
b110010 ,
b11001 '
b11001 )
b110001 $
b110001 %
#50
b110011 !
b110011 +
b110011 ,
b11010 &
b11010 (
#51
b110100 !
b110100 +
b110100 ,
b11010 '
b11010 )
b110011 $
b110011 %
#52
b110101 !
b110101 +
b110101 ,
b11011 &
b11011 (
#53
b110110 !
b110110 +
b110110 ,
b11011 '
b11011 )
b110101 $
b110101 %
#54
b110111 !
b110111 +
b110111 ,
b11100 &
b11100 (
#55
b111000 !
b111000 +
b111000 ,
b11100 '
b11100 )
b110111 $
b110111 %
#56
b111001 !
b111001 +
b111001 ,
b11101 &
b11101 (
#57
b111010 !
b111010 +
b111010 ,
b11101 '
b11101 )
b111001 $
b111001 %
#58
b111011 !
b111011 +
b111011 ,
b11110 &
b11110 (
#59
b111100 !
b111100 +
b111100 ,
b11110 '
b11110 )
b111011 $
b111011 %
#60
b111101 !
b111101 +
b111101 ,
b11111 &
b11111 (
#61
b111110 !
b111110 +
b111110 ,
b11111 '
b11111 )
b111101 $
b111101 %
#62
b111111 !
b111111 +
b111111 ,
b100000 &
b100000 (
#63
b1000000 !
b1000000 +
b1000000 ,
b100000 '
b100000 )
b111111 $
b111111 %
#64
b1000001 !
b1000001 +
b1000001 ,
b100001 &
b100001 (
#65
b1000010 !
b1000010 +
b1000010 ,
b100001 '
b100001 )
b1000001 $
b1000001 %
#66
b1000011 !
b1000011 +
b1000011 ,
b100010 &
b100010 (
#67
b1000100 !
b1000100 +
b1000100 ,
b100010 '
b100010 )
b1000011 $
b1000011 %
#68
b1000101 !
b1000101 +
b1000101 ,
b100011 &
b100011 (
#69
b1000110 !
b1000110 +
b1000110 ,
b100011 '
b100011 )
b1000101 $
b1000101 %
#70
b1000111 !
b1000111 +
b1000111 ,
b100100 &
b100100 (
#71
b1001000 !
b1001000 +
b1001000 ,
b100100 '
b100100 )
b1000111 $
b1000111 %
#72
b1001001 !
b1001001 +
b1001001 ,
b100101 &
b100101 (
#73
b1001010 !
b1001010 +
b1001010 ,
b100101 '
b100101 )
b1001001 $
b1001001 %
#74
b1001011 !
b1001011 +
b1001011 ,
b100110 &
b100110 (
#75
b1001100 !
b1001100 +
b1001100 ,
b100110 '
b100110 )
b1001011 $
b1001011 %
#76
b1001101 !
b1001101 +
b1001101 ,
b100111 &
b100111 (
#77
b1001110 !
b1001110 +
b1001110 ,
b100111 '
b100111 )
b1001101 $
b1001101 %
#78
b1001111 !
b1001111 +
b1001111 ,
b101000 &
b101000 (
#79
b1010000 !
b1010000 +
b1010000 ,
b101000 '
b101000 )
b1001111 $
b1001111 %
#80
b1010001 !
b1010001 +
b1010001 ,
b101001 &
b101001 (
#81
b1010010 !
b1010010 +
b1010010 ,
b101001 '
b101001 )
b1010001 $
b1010001 %
#82
b1010011 !
b1010011 +
b1010011 ,
b101010 &
b101010 (
#83
b1010100 !
b1010100 +
b1010100 ,
b101010 '
b101010 )
b1010011 $
b1010011 %
#84
b1010101 !
b1010101 +
b1010101 ,
b101011 &
b101011 (
#85
b1010110 !
b1010110 +
b1010110 ,
b101011 '
b101011 )
b1010101 $
b1010101 %
#86
b1010111 !
b1010111 +
b1010111 ,
b101100 &
b101100 (
#87
b1011000 !
b1011000 +
b1011000 ,
b101100 '
b101100 )
b1010111 $
b1010111 %
#88
b1011001 !
b1011001 +
b1011001 ,
b101101 &
b101101 (
#89
b1011010 !
b1011010 +
b1011010 ,
b101101 '
b101101 )
b1011001 $
b1011001 %
#90
b1011011 !
b1011011 +
b1011011 ,
b101110 &
b101110 (
#91
b1011100 !
b1011100 +
b1011100 ,
b101110 '
b101110 )
b1011011 $
b1011011 %
#92
b1011101 !
b1011101 +
b1011101 ,
b101111 &
b101111 (
#93
b1011110 !
b1011110 +
b1011110 ,
b101111 '
b101111 )
b1011101 $
b1011101 %
#94
b1011111 !
b1011111 +
b1011111 ,
b110000 &
b110000 (
#95
b1100000 !
b1100000 +
b1100000 ,
b110000 '
b110000 )
b1011111 $
b1011111 %
#96
b1100001 !
b1100001 +
b1100001 ,
b110001 &
b110001 (
#97
b1100010 !
b1100010 +
b1100010 ,
b110001 '
b110001 )
b1100001 $
b1100001 %
#98
b1100011 !
b1100011 +
b1100011 ,
b110010 &
b110010 (
#99
b1100100 !
b1100100 +
b1100100 ,
b110010 '
b110010 )
b1100011 $
b1100011 %
#100
b1100101 !
b1100101 +
b1100101 ,
b110011 &
b110011 (
#101
b1100110 !
b1100110 +
b1100110 ,
b110011 '
b110011 )
b1100101 $
b1100101 %
#102
b1100111 !
b1100111 +
b1100111 ,
b110100 &
b110100 (
#103
b1101000 !
b1101000 +
b1101000 ,
b110100 '
b110100 )
b1100111 $
b1100111 %
#104
b1101001 !
b1101001 +
b1101001 ,
b110101 &
b110101 (
#105
b1101010 !
b1101010 +
b1101010 ,
b110101 '
b110101 )
b1101001 $
b1101001 %
#106
b1101011 !
b1101011 +
b1101011 ,
b110110 &
b110110 (
#107
b1101100 !
b1101100 +
b1101100 ,
b110110 '
b110110 )
b1101011 $
b1101011 %
#108
b1101101 !
b1101101 +
b1101101 ,
b110111 &
b110111 (
#109
b1101110 !
b1101110 +
b1101110 ,
b110111 '
b110111 )
b1101101 $
b1101101 %
#110
b1101111 !
b1101111 +
b1101111 ,
b111000 &
b111000 (
#111
b1110000 !
b1110000 +
b1110000 ,
b111000 '
b111000 )
b1101111 $
b1101111 %
#112
b1110001 !
b1110001 +
b1110001 ,
b111001 &
b111001 (
#113
b1110010 !
b1110010 +
b1110010 ,
b111001 '
b111001 )
b1110001 $
b1110001 %
#114
b1110011 !
b1110011 +
b1110011 ,
b111010 &
b111010 (
#115
b1110100 !
b1110100 +
b1110100 ,
b111010 '
b111010 )
b1110011 $
b1110011 %
#116
b1110101 !
b1110101 +
b1110101 ,
b111011 &
b111011 (
#117
b1110110 !
b1110110 +
b1110110 ,
b111011 '
b111011 )
b1110101 $
b1110101 %
#118
b1110111 !
b1110111 +
b1110111 ,
b111100 &
b111100 (
#119
b1111000 !
b1111000 +
b1111000 ,
b111100 '
b111100 )
b1110111 $
b1110111 %
#120
b1111001 !
b1111001 +
b1111001 ,
b111101 &
b111101 (
#121
b1111010 !
b1111010 +
b1111010 ,
b111101 '
b111101 )
b1111001 $
b1111001 %
#122
b1111011 !
b1111011 +
b1111011 ,
b111110 &
b111110 (
#123
b1111100 !
b1111100 +
b1111100 ,
b111110 '
b111110 )
b1111011 $
b1111011 %
#124
b1111101 !
b1111101 +
b1111101 ,
b111111 &
b111111 (
#125
b1111110 !
b1111110 +
b1111110 ,
b111111 '
b111111 )
b1111101 $
b1111101 %
#126
b1111111 !
b1111111 +
b1111111 ,
b1000000 &
b1000000 (
#127
b10000000 !
b10000000 +
b10000000 ,
b1000000 '
b1000000 )
b1111111 $
b1111111 %
#128
b10000001 !
b10000001 +
b10000001 ,
b1000001 &
b1000001 (
#129
b10000010 !
b10000010 +
b10000010 ,
b1000001 '
b1000001 )
b10000001 $
b10000001 %
#130
b10000011 !
b10000011 +
b10000011 ,
b1000010 &
b1000010 (
#131
b10000100 !
b10000100 +
b10000100 ,
b1000010 '
b1000010 )
b10000011 $
b10000011 %
#132
b10000101 !
b10000101 +
b10000101 ,
b1000011 &
b1000011 (
#133
b10000110 !
b10000110 +
b10000110 ,
b1000011 '
b1000011 )
b10000101 $
b10000101 %
#134
b10000111 !
b10000111 +
b10000111 ,
b1000100 &
b1000100 (
#135
b10001000 !
b10001000 +
b10001000 ,
b1000100 '
b1000100 )
b10000111 $
b10000111 %
#136
b10001001 !
b10001001 +
b10001001 ,
b1000101 &
b1000101 (
#137
b10001010 !
b10001010 +
b10001010 ,
b1000101 '
b1000101 )
b10001001 $
b10001001 %
#138
b10001011 !
b10001011 +
b10001011 ,
b1000110 &
b1000110 (
#139
b10001100 !
b10001100 +
b10001100 ,
b1000110 '
b1000110 )
b10001011 $
b10001011 %
#140
b10001101 !
b10001101 +
b10001101 ,
b1000111 &
b1000111 (
#141
b10001110 !
b10001110 +
b10001110 ,
b1000111 '
b1000111 )
b10001101 $
b10001101 %
#142
b10001111 !
b10001111 +
b10001111 ,
b1001000 &
b1001000 (
#143
b10010000 !
b10010000 +
b10010000 ,
b1001000 '
b1001000 )
b10001111 $
b10001111 %
#144
b10010001 !
b10010001 +
b10010001 ,
b1001001 &
b1001001 (
#145
b10010010 !
b10010010 +
b10010010 ,
b1001001 '
b1001001 )
b10010001 $
b10010001 %
#146
b10010011 !
b10010011 +
b10010011 ,
b1001010 &
b1001010 (
#147
b10010100 !
b10010100 +
b10010100 ,
b1001010 '
b1001010 )
b10010011 $
b10010011 %
#148
b10010101 !
b10010101 +
b10010101 ,
b1001011 &
b1001011 (
#149
b10010110 !
b10010110 +
b10010110 ,
b1001011 '
b1001011 )
b10010101 $
b10010101 %
#150
b10010111 !
b10010111 +
b10010111 ,
b1001100 &
b1001100 (
#151
b10011000 !
b10011000 +
b10011000 ,
b1001100 '
b1001100 )
b10010111 $
b10010111 %
#152
b10011001 !
b10011001 +
b10011001 ,
b1001101 &
b1001101 (
#153
b10011010 !
b10011010 +
b10011010 ,
b1001101 '
b1001101 )
b10011001 $
b10011001 %
#154
b10011011 !
b10011011 +
b10011011 ,
b1001110 &
b1001110 (
#155
b10011100 !
b10011100 +
b10011100 ,
b1001110 '
b1001110 )
b10011011 $
b10011011 %
#156
b10011101 !
b10011101 +
b10011101 ,
b1001111 &
b1001111 (
#157
b10011110 !
b10011110 +
b10011110 ,
b1001111 '
b1001111 )
b10011101 $
b10011101 %
#158
b10011111 !
b10011111 +
b10011111 ,
b1010000 &
b1010000 (
#159
b10100000 !
b10100000 +
b10100000 ,
b1010000 '
b1010000 )
b10011111 $
b10011111 %
#160
b10100001 !
b10100001 +
b10100001 ,
b1010001 &
b1010001 (
#161
b10100010 !
b10100010 +
b10100010 ,
b1010001 '
b1010001 )
b10100001 $
b10100001 %
#162
b10100011 !
b10100011 +
b10100011 ,
b1010010 &
b1010010 (
#163
b10100100 !
b10100100 +
b10100100 ,
b1010010 '
b1010010 )
b10100011 $
b10100011 %
#164
b10100101 !
b10100101 +
b10100101 ,
b1010011 &
b1010011 (
#165
b10100110 !
b10100110 +
b10100110 ,
b1010011 '
b1010011 )
b10100101 $
b10100101 %
#166
b10100111 !
b10100111 +
b10100111 ,
b1010100 &
b1010100 (
#167
b10101000 !
b10101000 +
b10101000 ,
b1010100 '
b1010100 )
b10100111 $
b10100111 %
#168
b10101001 !
b10101001 +
b10101001 ,
b1010101 &
b1010101 (
#169
b10101010 !
b10101010 +
b10101010 ,
b1010101 '
b1010101 )
b10101001 $
b10101001 %
#170
b10101011 !
b10101011 +
b10101011 ,
b1010110 &
b1010110 (
#171
b10101100 !
b10101100 +
b10101100 ,
b1010110 '
b1010110 )
b10101011 $
b10101011 %
#172
b10101101 !
b10101101 +
b10101101 ,
b1010111 &
b1010111 (
#173
b10101110 !
b10101110 +
b10101110 ,
b1010111 '
b1010111 )
b10101101 $
b10101101 %
#174
b10101111 !
b10101111 +
b10101111 ,
b1011000 &
b1011000 (
#175
b10110000 !
b10110000 +
b10110000 ,
b1011000 '
b1011000 )
b10101111 $
b10101111 %
#176
b10110001 !
b10110001 +
b10110001 ,
b1011001 &
b1011001 (
#177
b10110010 !
b10110010 +
b10110010 ,
b1011001 '
b1011001 )
b10110001 $
b10110001 %
#178
b10110011 !
b10110011 +
b10110011 ,
b1011010 &
b1011010 (
#179
b10110100 !
b10110100 +
b10110100 ,
b1011010 '
b1011010 )
b10110011 $
b10110011 %
#180
b10110101 !
b10110101 +
b10110101 ,
b1011011 &
b1011011 (
#181
b10110110 !
b10110110 +
b10110110 ,
b1011011 '
b1011011 )
b10110101 $
b10110101 %
#182
b10110111 !
b10110111 +
b10110111 ,
b1011100 &
b1011100 (
#183
b10111000 !
b10111000 +
b10111000 ,
b1011100 '
b1011100 )
b10110111 $
b10110111 %
#184
b10111001 !
b10111001 +
b10111001 ,
b1011101 &
b1011101 (
#185
b10111010 !
b10111010 +
b10111010 ,
b1011101 '
b1011101 )
b10111001 $
b10111001 %
#186
b10111011 !
b10111011 +
b10111011 ,
b1011110 &
b1011110 (
#187
b10111100 !
b10111100 +
b10111100 ,
b1011110 '
b1011110 )
b10111011 $
b10111011 %
#188
b10111101 !
b10111101 +
b10111101 ,
b1011111 &
b1011111 (
#189
b10111110 !
b10111110 +
b10111110 ,
b1011111 '
b1011111 )
b10111101 $
b10111101 %
#190
b10111111 !
b10111111 +
b10111111 ,
b1100000 &
b1100000 (
#191
b11000000 !
b11000000 +
b11000000 ,
b1100000 '
b1100000 )
b10111111 $
b10111111 %
#192
b11000001 !
b11000001 +
b11000001 ,
b1100001 &
b1100001 (
#193
b11000010 !
b11000010 +
b11000010 ,
b1100001 '
b1100001 )
b11000001 $
b11000001 %
#194
b11000011 !
b11000011 +
b11000011 ,
b1100010 &
b1100010 (
#195
b11000100 !
b11000100 +
b11000100 ,
b1100010 '
b1100010 )
b11000011 $
b11000011 %
#196
b11000101 !
b11000101 +
b11000101 ,
b1100011 &
b1100011 (
#197
b11000110 !
b11000110 +
b11000110 ,
b1100011 '
b1100011 )
b11000101 $
b11000101 %
#198
b11000111 !
b11000111 +
b11000111 ,
b1100100 &
b1100100 (
#199
b11001000 !
b11001000 +
b11001000 ,
b1100100 '
b1100100 )
b11000111 $
b11000111 %
#200
b11001001 !
b11001001 +
b11001001 ,
b1100101 &
b1100101 (
#201
b11001010 !
b11001010 +
b11001010 ,
b1100101 '
b1100101 )
b11001001 $
b11001001 %
#202
b11001011 !
b11001011 +
b11001011 ,
b1100110 &
b1100110 (
#203
b11001100 !
b11001100 +
b11001100 ,
b1100110 '
b1100110 )
b11001011 $
b11001011 %
#204
b11001101 !
b11001101 +
b11001101 ,
b1100111 &
b1100111 (
#205
b11001110 !
b11001110 +
b11001110 ,
b1100111 '
b1100111 )
b11001101 $
b11001101 %
#206
b11001111 !
b11001111 +
b11001111 ,
b1101000 &
b1101000 (
#207
b11010000 !
b11010000 +
b11010000 ,
b1101000 '
b1101000 )
b11001111 $
b11001111 %
#208
b11010001 !
b11010001 +
b11010001 ,
b1101001 &
b1101001 (
#209
b11010010 !
b11010010 +
b11010010 ,
b1101001 '
b1101001 )
b11010001 $
b11010001 %
#210
b11010011 !
b11010011 +
b11010011 ,
b1101010 &
b1101010 (
#211
b11010100 !
b11010100 +
b11010100 ,
b1101010 '
b1101010 )
b11010011 $
b11010011 %
#212
b11010101 !
b11010101 +
b11010101 ,
b1101011 &
b1101011 (
#213
b11010110 !
b11010110 +
b11010110 ,
b1101011 '
b1101011 )
b11010101 $
b11010101 %
#214
b11010111 !
b11010111 +
b11010111 ,
b1101100 &
b1101100 (
#215
b11011000 !
b11011000 +
b11011000 ,
b1101100 '
b1101100 )
b11010111 $
b11010111 %
#216
b11011001 !
b11011001 +
b11011001 ,
b1101101 &
b1101101 (
#217
b11011010 !
b11011010 +
b11011010 ,
b1101101 '
b1101101 )
b11011001 $
b11011001 %
#218
b11011011 !
b11011011 +
b11011011 ,
b1101110 &
b1101110 (
#219
b11011100 !
b11011100 +
b11011100 ,
b1101110 '
b1101110 )
b11011011 $
b11011011 %
#220
b11011101 !
b11011101 +
b11011101 ,
b1101111 &
b1101111 (
#221
b11011110 !
b11011110 +
b11011110 ,
b1101111 '
b1101111 )
b11011101 $
b11011101 %
#222
b11011111 !
b11011111 +
b11011111 ,
b1110000 &
b1110000 (
#223
b11100000 !
b11100000 +
b11100000 ,
b1110000 '
b1110000 )
b11011111 $
b11011111 %
#224
b11100001 !
b11100001 +
b11100001 ,
b1110001 &
b1110001 (
#225
b11100010 !
b11100010 +
b11100010 ,
b1110001 '
b1110001 )
b11100001 $
b11100001 %
#226
b11100011 !
b11100011 +
b11100011 ,
b1110010 &
b1110010 (
#227
b11100100 !
b11100100 +
b11100100 ,
b1110010 '
b1110010 )
b11100011 $
b11100011 %
#228
b11100101 !
b11100101 +
b11100101 ,
b1110011 &
b1110011 (
#229
b11100110 !
b11100110 +
b11100110 ,
b1110011 '
b1110011 )
b11100101 $
b11100101 %
#230
b11100111 !
b11100111 +
b11100111 ,
b1110100 &
b1110100 (
#231
b11101000 !
b11101000 +
b11101000 ,
b1110100 '
b1110100 )
b11100111 $
b11100111 %
#232
b11101001 !
b11101001 +
b11101001 ,
b1110101 &
b1110101 (
#233
b11101010 !
b11101010 +
b11101010 ,
b1110101 '
b1110101 )
b11101001 $
b11101001 %
#234
b11101011 !
b11101011 +
b11101011 ,
b1110110 &
b1110110 (
#235
b11101100 !
b11101100 +
b11101100 ,
b1110110 '
b1110110 )
b11101011 $
b11101011 %
#236
b11101101 !
b11101101 +
b11101101 ,
b1110111 &
b1110111 (
#237
b11101110 !
b11101110 +
b11101110 ,
b1110111 '
b1110111 )
b11101101 $
b11101101 %
#238
b11101111 !
b11101111 +
b11101111 ,
b1111000 &
b1111000 (
#239
b11110000 !
b11110000 +
b11110000 ,
b1111000 '
b1111000 )
b11101111 $
b11101111 %
#240
b11110001 !
b11110001 +
b11110001 ,
b1111001 &
b1111001 (
#241
b11110010 !
b11110010 +
b11110010 ,
b1111001 '
b1111001 )
b11110001 $
b11110001 %
#242
b11110011 !
b11110011 +
b11110011 ,
b1111010 &
b1111010 (
#243
b11110100 !
b11110100 +
b11110100 ,
b1111010 '
b1111010 )
b11110011 $
b11110011 %
#244
b11110101 !
b11110101 +
b11110101 ,
b1111011 &
b1111011 (
#245
b11110110 !
b11110110 +
b11110110 ,
b1111011 '
b1111011 )
b11110101 $
b11110101 %
#246
b11110111 !
b11110111 +
b11110111 ,
b1111100 &
b1111100 (
#247
b11111000 !
b11111000 +
b11111000 ,
b1111100 '
b1111100 )
b11110111 $
b11110111 %
#248
b11111001 !
b11111001 +
b11111001 ,
b1111101 &
b1111101 (
#249
b11111010 !
b11111010 +
b11111010 ,
b1111101 '
b1111101 )
b11111001 $
b11111001 %
#250
b11111011 !
b11111011 +
b11111011 ,
b1111110 &
b1111110 (
#251
b11111100 !
b11111100 +
b11111100 ,
b1111110 '
b1111110 )
b11111011 $
b11111011 %
#252
b11111101 !
b11111101 +
b11111101 ,
b1111111 &
b1111111 (
#253
b11111110 !
b11111110 +
b11111110 ,
b1111111 '
b1111111 )
b11111101 $
b11111101 %
#254
b11111111 !
b11111111 +
b11111111 ,
b10000000 &
b10000000 (
#255
b100000000 !
b100000000 +
b100000000 ,
b10000000 '
b10000000 )
b11111111 $
b11111111 %
#256
b100000001 !
b100000001 +
b100000001 ,
b10000001 &
b10000001 (
#257
b100000010 !
b100000010 +
b100000010 ,
b10000001 '
b10000001 )
b100000001 $
b100000001 %
#258
b100000011 !
b100000011 +
b100000011 ,
b10000010 &
b10000010 (
#259
b100000100 !
b100000100 +
b100000100 ,
b10000010 '
b10000010 )
b100000011 $
b100000011 %
#260
b100000101 !
b100000101 +
b100000101 ,
b10000011 &
b10000011 (
#261
b100000110 !
b100000110 +
b100000110 ,
b10000011 '
b10000011 )
b100000101 $
b100000101 %
#262
b100000111 !
b100000111 +
b100000111 ,
b10000100 &
b10000100 (
#263
b100001000 !
b100001000 +
b100001000 ,
b10000100 '
b10000100 )
b100000111 $
b100000111 %
#264
b100001001 !
b100001001 +
b100001001 ,
b10000101 &
b10000101 (
#265
b100001010 !
b100001010 +
b100001010 ,
b10000101 '
b10000101 )
b100001001 $
b100001001 %
#266
b100001011 !
b100001011 +
b100001011 ,
b10000110 &
b10000110 (
#267
b100001100 !
b100001100 +
b100001100 ,
b10000110 '
b10000110 )
b100001011 $
b100001011 %
#268
b100001101 !
b100001101 +
b100001101 ,
b10000111 &
b10000111 (
#269
b100001110 !
b100001110 +
b100001110 ,
b10000111 '
b10000111 )
b100001101 $
b100001101 %
#270
b100001111 !
b100001111 +
b100001111 ,
b10001000 &
b10001000 (
#271
b100010000 !
b100010000 +
b100010000 ,
b10001000 '
b10001000 )
b100001111 $
b100001111 %
#272
b100010001 !
b100010001 +
b100010001 ,
b10001001 &
b10001001 (
#273
b100010010 !
b100010010 +
b100010010 ,
b10001001 '
b10001001 )
b100010001 $
b100010001 %
#274
b100010011 !
b100010011 +
b100010011 ,
b10001010 &
b10001010 (
#275
b100010100 !
b100010100 +
b100010100 ,
b10001010 '
b10001010 )
b100010011 $
b100010011 %
#276
b100010101 !
b100010101 +
b100010101 ,
b10001011 &
b10001011 (
#277
b100010110 !
b100010110 +
b100010110 ,
b10001011 '
b10001011 )
b100010101 $
b100010101 %
#278
b100010111 !
b100010111 +
b100010111 ,
b10001100 &
b10001100 (
#279
b100011000 !
b100011000 +
b100011000 ,
b10001100 '
b10001100 )
b100010111 $
b100010111 %
#280
b100011001 !
b100011001 +
b100011001 ,
b10001101 &
b10001101 (
#281
b100011010 !
b100011010 +
b100011010 ,
b10001101 '
b10001101 )
b100011001 $
b100011001 %
#282
b100011011 !
b100011011 +
b100011011 ,
b10001110 &
b10001110 (
#283
b100011100 !
b100011100 +
b100011100 ,
b10001110 '
b10001110 )
b100011011 $
b100011011 %
#284
b100011101 !
b100011101 +
b100011101 ,
b10001111 &
b10001111 (
#285
b100011110 !
b100011110 +
b100011110 ,
b10001111 '
b10001111 )
b100011101 $
b100011101 %
#286
b100011111 !
b100011111 +
b100011111 ,
b10010000 &
b10010000 (
#287
b100100000 !
b100100000 +
b100100000 ,
b10010000 '
b10010000 )
b100011111 $
b100011111 %
#288
b100100001 !
b100100001 +
b100100001 ,
b10010001 &
b10010001 (
#289
b100100010 !
b100100010 +
b100100010 ,
b10010001 '
b10010001 )
b100100001 $
b100100001 %
#290
b100100011 !
b100100011 +
b100100011 ,
b10010010 &
b10010010 (
#291
b100100100 !
b100100100 +
b100100100 ,
b10010010 '
b10010010 )
b100100011 $
b100100011 %
#292
b100100101 !
b100100101 +
b100100101 ,
b10010011 &
b10010011 (
#293
b100100110 !
b100100110 +
b100100110 ,
b10010011 '
b10010011 )
b100100101 $
b100100101 %
#294
b100100111 !
b100100111 +
b100100111 ,
b10010100 &
b10010100 (
#295
b100101000 !
b100101000 +
b100101000 ,
b10010100 '
b10010100 )
b100100111 $
b100100111 %
#296
b100101001 !
b100101001 +
b100101001 ,
b10010101 &
b10010101 (
#297
b100101010 !
b100101010 +
b100101010 ,
b10010101 '
b10010101 )
b100101001 $
b100101001 %
#298
b100101011 !
b100101011 +
b100101011 ,
b10010110 &
b10010110 (
#299
b100101100 !
b100101100 +
b100101100 ,
b10010110 '
b10010110 )
b100101011 $
b100101011 %
#300
b100101101 !
b100101101 +
b100101101 ,
b10010111 &
b10010111 (
#301
b100101110 !
b100101110 +
b100101110 ,
b10010111 '
b10010111 )
b100101101 $
b100101101 %
#302
b100101111 !
b100101111 +
b100101111 ,
b10011000 &
b10011000 (
#303
b100110000 !
b100110000 +
b100110000 ,
b10011000 '
b10011000 )
b100101111 $
b100101111 %
#304
b100110001 !
b100110001 +
b100110001 ,
b10011001 &
b10011001 (
#305
b100110010 !
b100110010 +
b100110010 ,
b10011001 '
b10011001 )
b100110001 $
b100110001 %
#306
b100110011 !
b100110011 +
b100110011 ,
b10011010 &
b10011010 (
#307
b100110100 !
b100110100 +
b100110100 ,
b10011010 '
b10011010 )
b100110011 $
b100110011 %
#308
b100110101 !
b100110101 +
b100110101 ,
b10011011 &
b10011011 (
#309
b100110110 !
b100110110 +
b100110110 ,
b10011011 '
b10011011 )
b100110101 $
b100110101 %
#310
b100110111 !
b100110111 +
b100110111 ,
b10011100 &
b10011100 (
#311
b100111000 !
b100111000 +
b100111000 ,
b10011100 '
b10011100 )
b100110111 $
b100110111 %
#312
b100111001 !
b100111001 +
b100111001 ,
b10011101 &
b10011101 (
#313
b100111010 !
b100111010 +
b100111010 ,
b10011101 '
b10011101 )
b100111001 $
b100111001 %
#314
b100111011 !
b100111011 +
b100111011 ,
b10011110 &
b10011110 (
#315
b100111100 !
b100111100 +
b100111100 ,
b10011110 '
b10011110 )
b100111011 $
b100111011 %
#316
b100111101 !
b100111101 +
b100111101 ,
b10011111 &
b10011111 (
#317
b100111110 !
b100111110 +
b100111110 ,
b10011111 '
b10011111 )
b100111101 $
b100111101 %
#318
b100111111 !
b100111111 +
b100111111 ,
b10100000 &
b10100000 (
#319
b101000000 !
b101000000 +
b101000000 ,
b10100000 '
b10100000 )
b100111111 $
b100111111 %
