e10_dump/rom.v
module rom(
    input logic[7:0] address,
    output logic[31:0] data
);
    reg [31:0] memory [256:0];
    
    initial begin
        integer i;
        for (i=0;i<256;i++) begin
            memory[i]=0;
        end
		//memory[1] = 32'hE3FF00CB; 
    end

    always_comb begin
        data=memory[address]; 
    end
endmodule

e10_dump/e10_dump.v
module e10_dump (); 

	logic [7:0] adr, d0, d1, d2, d3; 
	logic [9:0] badr; 
	logic [31:0] data; 
	logic [3:0] count; 
	
	
	initial begin
		$dumpfile("e10_dump.vcd"); 
		$dumpvars(0, e10_dump); 
		
		adr = 0; 
		
		repeat (256) begin 
			count = 0; 
			repeat (4) begin 
				#1; 
				badr = adr*4 + count; 
				$display("rom[%d]=%d", badr, (count == 0) ? d0 : (count == 1) ? d1 : (count == 2) ? d2 : d3); 
				count += 1; 
			end 
			adr += 1; 
		end 
	end 
	
	always @(*) begin 
		d0 = data[7:0]; 
		d1 = data[15:8];
		d2 = data[23:16];
		d3 = data[31:24]; 
	end 
	
	rom dut(adr, data); 
	
endmodule

e10_dump/e10_dump.vcd
$date
	Fri Nov 12 15:07:02 2021
$end
$version
	Icarus Verilog
$end
$timescale
	1s
$end
$scope module e10_dump $end
$var wire 32 ! data [31:0] $end
$var reg 8 " adr [7:0] $end
$var reg 10 # badr [9:0] $end
$var reg 4 $ count [3:0] $end
$var reg 8 % d0 [7:0] $end
$var reg 8 & d1 [7:0] $end
$var reg 8 ' d2 [7:0] $end
$var reg 8 ( d3 [7:0] $end
$scope module dut $end
$var wire 8 ) address [7:0] $end
$var reg 32 * data [31:0] $end
$scope begin $unm_blk_5 $end
$var integer 32 + i [31:0] $end
$upscope $end
$upscope $end
$upscope $end
$enddefinitions $end
#0
$dumpvars
b100000000 +
b0 *
b0 )
b0 (
b0 '
b0 &
b0 %
b0 $
bx #
b0 "
b0 !
$end
#1
b1 $
b0 #
#2
b10 $
b1 #
#3
b11 $
b10 #
#4
b11100011 (
b11111111 '
b11001011 %
b11100011111111110000000011001011 !
b11100011111111110000000011001011 *
b1 "
b1 )
b0 $
b11 #
#5
b1 $
b100 #
#6
b10 $
b101 #
#7
b11 $
b110 #
#8
b0 (
b0 '
b0 %
b0 !
b0 *
b10 "
b10 )
b0 $
b111 #
#9
b1 $
b1000 #
#10
b10 $
b1001 #
#11
b11 $
b1010 #
#12
b11 "
b11 )
b0 $
b1011 #
#13
b1 $
b1100 #
#14
b10 $
b1101 #
#15
b11 $
b1110 #
#16
b100 "
b100 )
b0 $
b1111 #
#17
b1 $
b10000 #
#18
b10 $
b10001 #
#19
b11 $
b10010 #
#20
b101 "
b101 )
b0 $
b10011 #
#21
b1 $
b10100 #
#22
b10 $
b10101 #
#23
b11 $
b10110 #
#24
b110 "
b110 )
b0 $
b10111 #
#25
b1 $
b11000 #
#26
b10 $
b11001 #
#27
b11 $
b11010 #
#28
b111 "
b111 )
b0 $
b11011 #
#29
b1 $
b11100 #
#30
b10 $
b11101 #
#31
b11 $
b11110 #
#32
b1000 "
b1000 )
b0 $
b11111 #
#33
b1 $
b100000 #
#34
b10 $
b100001 #
#35
b11 $
b100010 #
#36
b1001 "
b1001 )
b0 $
b100011 #
#37
b1 $
b100100 #
#38
b10 $
b100101 #
#39
b11 $
b100110 #
#40
b1010 "
b1010 )
b0 $
b100111 #
#41
b1 $
b101000 #
#42
b10 $
b101001 #
#43
b11 $
b101010 #
#44
b1011 "
b1011 )
b0 $
b101011 #
#45
b1 $
b101100 #
#46
b10 $
b101101 #
#47
b11 $
b101110 #
#48
b1100 "
b1100 )
b0 $
b101111 #
#49
b1 $
b110000 #
#50
b10 $
b110001 #
#51
b11 $
b110010 #
#52
b1101 "
b1101 )
b0 $
b110011 #
#53
b1 $
b110100 #
#54
b10 $
b110101 #
#55
b11 $
b110110 #
#56
b1110 "
b1110 )
b0 $
b110111 #
#57
b1 $
b111000 #
#58
b10 $
b111001 #
#59
b11 $
b111010 #
#60
b1111 "
b1111 )
b0 $
b111011 #
#61
b1 $
b111100 #
#62
b10 $
b111101 #
#63
b11 $
b111110 #
#64
b10000 "
b10000 )
b0 $
b111111 #
#65
b1 $
b1000000 #
#66
b10 $
b1000001 #
#67
b11 $
b1000010 #
#68
b10001 "
b10001 )
b0 $
b1000011 #
#69
b1 $
b1000100 #
#70
b10 $
b1000101 #
#71
b11 $
b1000110 #
#72
b10010 "
b10010 )
b0 $
b1000111 #
#73
b1 $
b1001000 #
#74
b10 $
b1001001 #
#75
b11 $
b1001010 #
#76
b10011 "
b10011 )
b0 $
b1001011 #
#77
b1 $
b1001100 #
#78
b10 $
b1001101 #
#79
b11 $
b1001110 #
#80
b10100 "
b10100 )
b0 $
b1001111 #
#81
b1 $
b1010000 #
#82
b10 $
b1010001 #
#83
b11 $
b1010010 #
#84
b10101 "
b10101 )
b0 $
b1010011 #
#85
b1 $
b1010100 #
#86
b10 $
b1010101 #
#87
b11 $
b1010110 #
#88
b10110 "
b10110 )
b0 $
b1010111 #
#89
b1 $
b1011000 #
#90
b10 $
b1011001 #
#91
b11 $
b1011010 #
#92
b10111 "
b10111 )
b0 $
b1011011 #
#93
b1 $
b1011100 #
#94
b10 $
b1011101 #
#95
b11 $
b1011110 #
#96
b11000 "
b11000 )
b0 $
b1011111 #
#97
b1 $
b1100000 #
#98
b10 $
b1100001 #
#99
b11 $
b1100010 #
#100
b11001 "
b11001 )
b0 $
b1100011 #
#101
b1 $
b1100100 #
#102
b10 $
b1100101 #
#103
b11 $
b1100110 #
#104
b11010 "
b11010 )
b0 $
b1100111 #
#105
b1 $
b1101000 #
#106
b10 $
b1101001 #
#107
b11 $
b1101010 #
#108
b11011 "
b11011 )
b0 $
b1101011 #
#109
b1 $
b1101100 #
#110
b10 $
b1101101 #
#111
b11 $
b1101110 #
#112
b11100 "
b11100 )
b0 $
b1101111 #
#113
b1 $
b1110000 #
#114
b10 $
b1110001 #
#115
b11 $
b1110010 #
#116
b11101 "
b11101 )
b0 $
b1110011 #
#117
b1 $
b1110100 #
#118
b10 $
b1110101 #
#119
b11 $
b1110110 #
#120
b11110 "
b11110 )
b0 $
b1110111 #
#121
b1 $
b1111000 #
#122
b10 $
b1111001 #
#123
b11 $
b1111010 #
#124
b11111 "
b11111 )
b0 $
b1111011 #
#125
b1 $
b1111100 #
#126
b10 $
b1111101 #
#127
b11 $
b1111110 #
#128
b100000 "
b100000 )
b0 $
b1111111 #
#129
b1 $
b10000000 #
#130
b10 $
b10000001 #
#131
b11 $
b10000010 #
#132
b100001 "
b100001 )
b0 $
b10000011 #
#133
b1 $
b10000100 #
#134
b10 $
b10000101 #
#135
b11 $
b10000110 #
#136
b100010 "
b100010 )
b0 $
b10000111 #
#137
b1 $
b10001000 #
#138
b10 $
b10001001 #
#139
b11 $
b10001010 #
#140
b100011 "
b100011 )
b0 $
b10001011 #
#141
b1 $
b10001100 #
#142
b10 $
b10001101 #
#143
b11 $
b10001110 #
#144
b100100 "
b100100 )
b0 $
b10001111 #
#145
b1 $
b10010000 #
#146
b10 $
b10010001 #
#147
b11 $
b10010010 #
#148
b100101 "
b100101 )
b0 $
b10010011 #
#149
b1 $
b10010100 #
#150
b10 $
b10010101 #
#151
b11 $
b10010110 #
#152
b100110 "
b100110 )
b0 $
b10010111 #
#153
b1 $
b10011000 #
#154
b10 $
b10011001 #
#155
b11 $
b10011010 #
#156
b100111 "
b100111 )
b0 $
b10011011 #
#157
b1 $
b10011100 #
#158
b10 $
b10011101 #
#159
b11 $
b10011110 #
#160
b101000 "
b101000 )
b0 $
b10011111 #
#161
b1 $
b10100000 #
#162
b10 $
b10100001 #
#163
b11 $
b10100010 #
#164
b101001 "
b101001 )
b0 $
b10100011 #
#165
b1 $
b10100100 #
#166
b10 $
b10100101 #
#167
b11 $
b10100110 #
#168
b101010 "
b101010 )
b0 $
b10100111 #
#169
b1 $
b10101000 #
#170
b10 $
b10101001 #
#171
b11 $
b10101010 #
#172
b101011 "
b101011 )
b0 $
b10101011 #
#173
b1 $
b10101100 #
#174
b10 $
b10101101 #
#175
b11 $
b10101110 #
#176
b101100 "
b101100 )
b0 $
b10101111 #
#177
b1 $
b10110000 #
#178
b10 $
b10110001 #
#179
b11 $
b10110010 #
#180
b101101 "
b101101 )
b0 $
b10110011 #
#181
b1 $
b10110100 #
#182
b10 $
b10110101 #
#183
b11 $
b10110110 #
#184
b101110 "
b101110 )
b0 $
b10110111 #
#185
b1 $
b10111000 #
#186
b10 $
b10111001 #
#187
b11 $
b10111010 #
#188
b101111 "
b101111 )
b0 $
b10111011 #
#189
b1 $
b10111100 #
#190
b10 $
b10111101 #
#191
b11 $
b10111110 #
#192
b110000 "
b110000 )
b0 $
b10111111 #
#193
b1 $
b11000000 #
#194
b10 $
b11000001 #
#195
b11 $
b11000010 #
#196
b110001 "
b110001 )
b0 $
b11000011 #
#197
b1 $
b11000100 #
#198
b10 $
b11000101 #
#199
b11 $
b11000110 #
#200
b110010 "
b110010 )
b0 $
b11000111 #
#201
b1 $
b11001000 #
#202
b10 $
b11001001 #
#203
b11 $
b11001010 #
#204
b110011 "
b110011 )
b0 $
b11001011 #
#205
b1 $
b11001100 #
#206
b10 $
b11001101 #
#207
b11 $
b11001110 #
#208
b110100 "
b110100 )
b0 $
b11001111 #
#209
b1 $
b11010000 #
#210
b10 $
b11010001 #
#211
b11 $
b11010010 #
#212
b110101 "
b110101 )
b0 $
b11010011 #
#213
b1 $
b11010100 #
#214
b10 $
b11010101 #
#215
b11 $
b11010110 #
#216
b110110 "
b110110 )
b0 $
b11010111 #
#217
b1 $
b11011000 #
#218
b10 $
b11011001 #
#219
b11 $
b11011010 #
#220
b110111 "
b110111 )
b0 $
b11011011 #
#221
b1 $
b11011100 #
#222
b10 $
b11011101 #
#223
b11 $
b11011110 #
#224
b111000 "
b111000 )
b0 $
b11011111 #
#225
b1 $
b11100000 #
#226
b10 $
b11100001 #
#227
b11 $
b11100010 #
#228
b111001 "
b111001 )
b0 $
b11100011 #
#229
b1 $
b11100100 #
#230
b10 $
b11100101 #
#231
b11 $
b11100110 #
#232
b111010 "
b111010 )
b0 $
b11100111 #
#233
b1 $
b11101000 #
#234
b10 $
b11101001 #
#235
b11 $
b11101010 #
#236
b111011 "
b111011 )
b0 $
b11101011 #
#237
b1 $
b11101100 #
#238
b10 $
b11101101 #
#239
b11 $
b11101110 #
#240
b111100 "
b111100 )
b0 $
b11101111 #
#241
b1 $
b11110000 #
#242
b10 $
b11110001 #
#243
b11 $
b11110010 #
#244
b111101 "
b111101 )
b0 $
b11110011 #
#245
b1 $
b11110100 #
#246
b10 $
b11110101 #
#247
b11 $
b11110110 #
#248
b111110 "
b111110 )
b0 $
b11110111 #
#249
b1 $
b11111000 #
#250
b10 $
b11111001 #
#251
b11 $
b11111010 #
#252
b111111 "
b111111 )
b0 $
b11111011 #
#253
b1 $
b11111100 #
#254
b10 $
b11111101 #
#255
b11 $
b11111110 #
#256
b1000000 "
b1000000 )
b0 $
b11111111 #
#257
b1 $
b100000000 #
#258
b10 $
b100000001 #
#259
b11 $
b100000010 #
#260
b1000001 "
b1000001 )
b0 $
b100000011 #
#261
b1 $
b100000100 #
#262
b10 $
b100000101 #
#263
b11 $
b100000110 #
#264
b1000010 "
b1000010 )
b0 $
b100000111 #
#265
b1 $
b100001000 #
#266
b10 $
b100001001 #
#267
b11 $
b100001010 #
#268
b1000011 "
b1000011 )
b0 $
b100001011 #
#269
b1 $
b100001100 #
#270
b10 $
b100001101 #
#271
b11 $
b100001110 #
#272
b1000100 "
b1000100 )
b0 $
b100001111 #
#273
b1 $
b100010000 #
#274
b10 $
b100010001 #
#275
b11 $
b100010010 #
#276
b1000101 "
b1000101 )
b0 $
b100010011 #
#277
b1 $
b100010100 #
#278
b10 $
b100010101 #
#279
b11 $
b100010110 #
#280
b1000110 "
b1000110 )
b0 $
b100010111 #
#281
b1 $
b100011000 #
#282
b10 $
b100011001 #
#283
b11 $
b100011010 #
#284
b1000111 "
b1000111 )
b0 $
b100011011 #
#285
b1 $
b100011100 #
#286
b10 $
b100011101 #
#287
b11 $
b100011110 #
#288
b1001000 "
b1001000 )
b0 $
b100011111 #
#289
b1 $
b100100000 #
#290
b10 $
b100100001 #
#291
b11 $
b100100010 #
#292
b1001001 "
b1001001 )
b0 $
b100100011 #
#293
b1 $
b100100100 #
#294
b10 $
b100100101 #
#295
b11 $
b100100110 #
#296
b1001010 "
b1001010 )
b0 $
b100100111 #
#297
b1 $
b100101000 #
#298
b10 $
b100101001 #
#299
b11 $
b100101010 #
#300
b1001011 "
b1001011 )
b0 $
b100101011 #
#301
b1 $
b100101100 #
#302
b10 $
b100101101 #
#303
b11 $
b100101110 #
#304
b1001100 "
b1001100 )
b0 $
b100101111 #
#305
b1 $
b100110000 #
#306
b10 $
b100110001 #
#307
b11 $
b100110010 #
#308
b1001101 "
b1001101 )
b0 $
b100110011 #
#309
b1 $
b100110100 #
#310
b10 $
b100110101 #
#311
b11 $
b100110110 #
#312
b1001110 "
b1001110 )
b0 $
b100110111 #
#313
b1 $
b100111000 #
#314
b10 $
b100111001 #
#315
b11 $
b100111010 #
#316
b1001111 "
b1001111 )
b0 $
b100111011 #
#317
b1 $
b100111100 #
#318
b10 $
b100111101 #
#319
b11 $
b100111110 #
#320
b1010000 "
b1010000 )
b0 $
b100111111 #
#321
b1 $
b101000000 #
#322
b10 $
b101000001 #
#323
b11 $
b101000010 #
#324
b1010001 "
b1010001 )
b0 $
b101000011 #
#325
b1 $
b101000100 #
#326
b10 $
b101000101 #
#327
b11 $
b101000110 #
#328
b1010010 "
b1010010 )
b0 $
b101000111 #
#329
b1 $
b101001000 #
#330
b10 $
b101001001 #
#331
b11 $
b101001010 #
#332
b1010011 "
b1010011 )
b0 $
b101001011 #
#333
b1 $
b101001100 #
#334
b10 $
b101001101 #
#335
b11 $
b101001110 #
#336
b1010100 "
b1010100 )
b0 $
b101001111 #
#337
b1 $
b101010000 #
#338
b10 $
b101010001 #
#339
b11 $
b101010010 #
#340
b1010101 "
b1010101 )
b0 $
b101010011 #
#341
b1 $
b101010100 #
#342
b10 $
b101010101 #
#343
b11 $
b101010110 #
#344
b1010110 "
b1010110 )
b0 $
b101010111 #
#345
b1 $
b101011000 #
#346
b10 $
b101011001 #
#347
b11 $
b101011010 #
#348
b1010111 "
b1010111 )
b0 $
b101011011 #
#349
b1 $
b101011100 #
#350
b10 $
b101011101 #
#351
b11 $
b101011110 #
#352
b1011000 "
b1011000 )
b0 $
b101011111 #
#353
b1 $
b101100000 #
#354
b10 $
b101100001 #
#355
b11 $
b101100010 #
#356
b1011001 "
b1011001 )
b0 $
b101100011 #
#357
b1 $
b101100100 #
#358
b10 $
b101100101 #
#359
b11 $
b101100110 #
#360
b1011010 "
b1011010 )
b0 $
b101100111 #
#361
b1 $
b101101000 #
#362
b10 $
b101101001 #
#363
b11 $
b101101010 #
#364
b1011011 "
b1011011 )
b0 $
b101101011 #
#365
b1 $
b101101100 #
#366
b10 $
b101101101 #
#367
b11 $
b101101110 #
#368
b1011100 "
b1011100 )
b0 $
b101101111 #
#369
b1 $
b101110000 #
#370
b10 $
b101110001 #
#371
b11 $
b101110010 #
#372
b1011101 "
b1011101 )
b0 $
b101110011 #
#373
b1 $
b101110100 #
#374
b10 $
b101110101 #
#375
b11 $
b101110110 #
#376
b1011110 "
b1011110 )
b0 $
b101110111 #
#377
b1 $
b101111000 #
#378
b10 $
b101111001 #
#379
b11 $
b101111010 #
#380
b1011111 "
b1011111 )
b0 $
b101111011 #
#381
b1 $
b101111100 #
#382
b10 $
b101111101 #
#383
b11 $
b101111110 #
#384
b1100000 "
b1100000 )
b0 $
b101111111 #
#385
b1 $
b110000000 #
#386
b10 $
b110000001 #
#387
b11 $
b110000010 #
#388
b1100001 "
b1100001 )
b0 $
b110000011 #
#389
b1 $
b110000100 #
#390
b10 $
b110000101 #
#391
b11 $
b110000110 #
#392
b1100010 "
b1100010 )
b0 $
b110000111 #
#393
b1 $
b110001000 #
#394
b10 $
b110001001 #
#395
b11 $
b110001010 #
#396
b1100011 "
b1100011 )
b0 $
b110001011 #
#397
b1 $
b110001100 #
#398
b10 $
b110001101 #
#399
b11 $
b110001110 #
#400
b1100100 "
b1100100 )
b0 $
b110001111 #
#401
b1 $
b110010000 #
#402
b10 $
b110010001 #
#403
b11 $
b110010010 #
#404
b1100101 "
b1100101 )
b0 $
b110010011 #
#405
b1 $
b110010100 #
#406
b10 $
b110010101 #
#407
b11 $
b110010110 #
#408
b1100110 "
b1100110 )
b0 $
b110010111 #
#409
b1 $
b110011000 #
#410
b10 $
b110011001 #
#411
b11 $
b110011010 #
#412
b1100111 "
b1100111 )
b0 $
b110011011 #
#413
b1 $
b110011100 #
#414
b10 $
b110011101 #
#415
b11 $
b110011110 #
#416
b1101000 "
b1101000 )
b0 $
b110011111 #
#417
b1 $
b110100000 #
#418
b10 $
b110100001 #
#419
b11 $
b110100010 #
#420
b1101001 "
b1101001 )
b0 $
b110100011 #
#421
b1 $
b110100100 #
#422
b10 $
b110100101 #
#423
b11 $
b110100110 #
#424
b1101010 "
b1101010 )
b0 $
b110100111 #
#425
b1 $
b110101000 #
#426
b10 $
b110101001 #
#427
b11 $
b110101010 #
#428
b1101011 "
b1101011 )
b0 $
b110101011 #
#429
b1 $
b110101100 #
#430
b10 $
b110101101 #
#431
b11 $
b110101110 #
#432
b1101100 "
b1101100 )
b0 $
b110101111 #
#433
b1 $
b110110000 #
#434
b10 $
b110110001 #
#435
b11 $
b110110010 #
#436
b1101101 "
b1101101 )
b0 $
b110110011 #
#437
b1 $
b110110100 #
#438
b10 $
b110110101 #
#439
b11 $
b110110110 #
#440
b1101110 "
b1101110 )
b0 $
b110110111 #
#441
b1 $
b110111000 #
#442
b10 $
b110111001 #
#443
b11 $
b110111010 #
#444
b1101111 "
b1101111 )
b0 $
b110111011 #
#445
b1 $
b110111100 #
#446
b10 $
b110111101 #
#447
b11 $
b110111110 #
#448
b1110000 "
b1110000 )
b0 $
b110111111 #
#449
b1 $
b111000000 #
#450
b10 $
b111000001 #
#451
b11 $
b111000010 #
#452
b1110001 "
b1110001 )
b0 $
b111000011 #
#453
b1 $
b111000100 #
#454
b10 $
b111000101 #
#455
b11 $
b111000110 #
#456
b1110010 "
b1110010 )
b0 $
b111000111 #
#457
b1 $
b111001000 #
#458
b10 $
b111001001 #
#459
b11 $
b111001010 #
#460
b1110011 "
b1110011 )
b0 $
b111001011 #
#461
b1 $
b111001100 #
#462
b10 $
b111001101 #
#463
b11 $
b111001110 #
#464
b1110100 "
b1110100 )
b0 $
b111001111 #
#465
b1 $
b111010000 #
#466
b10 $
b111010001 #
#467
b11 $
b111010010 #
#468
b1110101 "
b1110101 )
b0 $
b111010011 #
#469
b1 $
b111010100 #
#470
b10 $
b111010101 #
#471
b11 $
b111010110 #
#472
b1110110 "
b1110110 )
b0 $
b111010111 #
#473
b1 $
b111011000 #
#474
b10 $
b111011001 #
#475
b11 $
b111011010 #
#476
b1110111 "
b1110111 )
b0 $
b111011011 #
#477
b1 $
b111011100 #
#478
b10 $
b111011101 #
#479
b11 $
b111011110 #
#480
b1111000 "
b1111000 )
b0 $
b111011111 #
#481
b1 $
b111100000 #
#482
b10 $
b111100001 #
#483
b11 $
b111100010 #
#484
b1111001 "
b1111001 )
b0 $
b111100011 #
#485
b1 $
b111100100 #
#486
b10 $
b111100101 #
#487
b11 $
b111100110 #
#488
b1111010 "
b1111010 )
b0 $
b111100111 #
#489
b1 $
b111101000 #
#490
b10 $
b111101001 #
#491
b11 $
b111101010 #
#492
b1111011 "
b1111011 )
b0 $
b111101011 #
#493
b1 $
b111101100 #
#494
b10 $
b111101101 #
#495
b11 $
b111101110 #
#496
b1111100 "
b1111100 )
b0 $
b111101111 #
#497
b1 $
b111110000 #
#498
b10 $
b111110001 #
#499
b11 $
b111110010 #
#500
b1111101 "
b1111101 )
b0 $
b111110011 #
#501
b1 $
b111110100 #
#502
b10 $
b111110101 #
#503
b11 $
b111110110 #
#504
b1111110 "
b1111110 )
b0 $
b111110111 #
#505
b1 $
b111111000 #
#506
b10 $
b111111001 #
#507
b11 $
b111111010 #
#508
b1111111 "
b1111111 )
b0 $
b111111011 #
#509
b1 $
b111111100 #
#510
b10 $
b111111101 #
#511
b11 $
b111111110 #
#512
b10000000 "
b10000000 )
b0 $
b111111111 #
#513
b1 $
b1000000000 #
#514
b10 $
b1000000001 #
#515
b11 $
b1000000010 #
#516
b10000001 "
b10000001 )
b0 $
b1000000011 #
#517
b1 $
b1000000100 #
#518
b10 $
b1000000101 #
#519
b11 $
b1000000110 #
#520
b10000010 "
b10000010 )
b0 $
b1000000111 #
#521
b1 $
b1000001000 #
#522
b10 $
b1000001001 #
#523
b11 $
b1000001010 #
#524
b10000011 "
b10000011 )
b0 $
b1000001011 #
#525
b1 $
b1000001100 #
#526
b10 $
b1000001101 #
#527
b11 $
b1000001110 #
#528
b10000100 "
b10000100 )
b0 $
b1000001111 #
#529
b1 $
b1000010000 #
#530
b10 $
b1000010001 #
#531
b11 $
b1000010010 #
#532
b10000101 "
b10000101 )
b0 $
b1000010011 #
#533
b1 $
b1000010100 #
#534
b10 $
b1000010101 #
#535
b11 $
b1000010110 #
#536
b10000110 "
b10000110 )
b0 $
b1000010111 #
#537
b1 $
b1000011000 #
#538
b10 $
b1000011001 #
#539
b11 $
b1000011010 #
#540
b10000111 "
b10000111 )
b0 $
b1000011011 #
#541
b1 $
b1000011100 #
#542
b10 $
b1000011101 #
#543
b11 $
b1000011110 #
#544
b10001000 "
b10001000 )
b0 $
b1000011111 #
#545
b1 $
b1000100000 #
#546
b10 $
b1000100001 #
#547
b11 $
b1000100010 #
#548
b10001001 "
b10001001 )
b0 $
b1000100011 #
#549
b1 $
b1000100100 #
#550
b10 $
b1000100101 #
#551
b11 $
b1000100110 #
#552
b10001010 "
b10001010 )
b0 $
b1000100111 #
#553
b1 $
b1000101000 #
#554
b10 $
b1000101001 #
#555
b11 $
b1000101010 #
#556
b10001011 "
b10001011 )
b0 $
b1000101011 #
#557
b1 $
b1000101100 #
#558
b10 $
b1000101101 #
#559
b11 $
b1000101110 #
#560
b10001100 "
b10001100 )
b0 $
b1000101111 #
#561
b1 $
b1000110000 #
#562
b10 $
b1000110001 #
#563
b11 $
b1000110010 #
#564
b10001101 "
b10001101 )
b0 $
b1000110011 #
#565
b1 $
b1000110100 #
#566
b10 $
b1000110101 #
#567
b11 $
b1000110110 #
#568
b10001110 "
b10001110 )
b0 $
b1000110111 #
#569
b1 $
b1000111000 #
#570
b10 $
b1000111001 #
#571
b11 $
b1000111010 #
#572
b10001111 "
b10001111 )
b0 $
b1000111011 #
#573
b1 $
b1000111100 #
#574
b10 $
b1000111101 #
#575
b11 $
b1000111110 #
#576
b10010000 "
b10010000 )
b0 $
b1000111111 #
#577
b1 $
b1001000000 #
#578
b10 $
b1001000001 #
#579
b11 $
b1001000010 #
#580
b10010001 "
b10010001 )
b0 $
b1001000011 #
#581
b1 $
b1001000100 #
#582
b10 $
b1001000101 #
#583
b11 $
b1001000110 #
#584
b10010010 "
b10010010 )
b0 $
b1001000111 #
#585
b1 $
b1001001000 #
#586
b10 $
b1001001001 #
#587
b11 $
b1001001010 #
#588
b10010011 "
b10010011 )
b0 $
b1001001011 #
#589
b1 $
b1001001100 #
#590
b10 $
b1001001101 #
#591
b11 $
b1001001110 #
#592
b10010100 "
b10010100 )
b0 $
b1001001111 #
#593
b1 $
b1001010000 #
#594
b10 $
b1001010001 #
#595
b11 $
b1001010010 #
#596
b10010101 "
b10010101 )
b0 $
b1001010011 #
#597
b1 $
b1001010100 #
#598
b10 $
b1001010101 #
#599
b11 $
b1001010110 #
#600
b10010110 "
b10010110 )
b0 $
b1001010111 #
#601
b1 $
b1001011000 #
#602
b10 $
b1001011001 #
#603
b11 $
b1001011010 #
#604
b10010111 "
b10010111 )
b0 $
b1001011011 #
#605
b1 $
b1001011100 #
#606
b10 $
b1001011101 #
#607
b11 $
b1001011110 #
#608
b10011000 "
b10011000 )
b0 $
b1001011111 #
#609
b1 $
b1001100000 #
#610
b10 $
b1001100001 #
#611
b11 $
b1001100010 #
#612
b10011001 "
b10011001 )
b0 $
b1001100011 #
#613
b1 $
b1001100100 #
#614
b10 $
b1001100101 #
#615
b11 $
b1001100110 #
#616
b10011010 "
b10011010 )
b0 $
b1001100111 #
#617
b1 $
b1001101000 #
#618
b10 $
b1001101001 #
#619
b11 $
b1001101010 #
#620
b10011011 "
b10011011 )
b0 $
b1001101011 #
#621
b1 $
b1001101100 #
#622
b10 $
b1001101101 #
#623
b11 $
b1001101110 #
#624
b10011100 "
b10011100 )
b0 $
b1001101111 #
#625
b1 $
b1001110000 #
#626
b10 $
b1001110001 #
#627
b11 $
b1001110010 #
#628
b10011101 "
b10011101 )
b0 $
b1001110011 #
#629
b1 $
b1001110100 #
#630
b10 $
b1001110101 #
#631
b11 $
b1001110110 #
#632
b10011110 "
b10011110 )
b0 $
b1001110111 #
#633
b1 $
b1001111000 #
#634
b10 $
b1001111001 #
#635
b11 $
b1001111010 #
#636
b10011111 "
b10011111 )
b0 $
b1001111011 #
#637
b1 $
b1001111100 #
#638
b10 $
b1001111101 #
#639
b11 $
b1001111110 #
#640
b10100000 "
b10100000 )
b0 $
b1001111111 #
#641
b1 $
b1010000000 #
#642
b10 $
b1010000001 #
#643
b11 $
b1010000010 #
#644
b10100001 "
b10100001 )
b0 $
b1010000011 #
#645
b1 $
b1010000100 #
#646
b10 $
b1010000101 #
#647
b11 $
b1010000110 #
#648
b10100010 "
b10100010 )
b0 $
b1010000111 #
#649
b1 $
b1010001000 #
#650
b10 $
b1010001001 #
#651
b11 $
b1010001010 #
#652
b10100011 "
b10100011 )
b0 $
b1010001011 #
#653
b1 $
b1010001100 #
#654
b10 $
b1010001101 #
#655
b11 $
b1010001110 #
#656
b10100100 "
b10100100 )
b0 $
b1010001111 #
#657
b1 $
b1010010000 #
#658
b10 $
b1010010001 #
#659
b11 $
b1010010010 #
#660
b10100101 "
b10100101 )
b0 $
b1010010011 #
#661
b1 $
b1010010100 #
#662
b10 $
b1010010101 #
#663
b11 $
b1010010110 #
#664
b10100110 "
b10100110 )
b0 $
b1010010111 #
#665
b1 $
b1010011000 #
#666
b10 $
b1010011001 #
#667
b11 $
b1010011010 #
#668
b10100111 "
b10100111 )
b0 $
b1010011011 #
#669
b1 $
b1010011100 #
#670
b10 $
b1010011101 #
#671
b11 $
b1010011110 #
#672
b10101000 "
b10101000 )
b0 $
b1010011111 #
#673
b1 $
b1010100000 #
#674
b10 $
b1010100001 #
#675
b11 $
b1010100010 #
#676
b10101001 "
b10101001 )
b0 $
b1010100011 #
#677
b1 $
b1010100100 #
#678
b10 $
b1010100101 #
#679
b11 $
b1010100110 #
#680
b10101010 "
b10101010 )
b0 $
b1010100111 #
#681
b1 $
b1010101000 #
#682
b10 $
b1010101001 #
#683
b11 $
b1010101010 #
#684
b10101011 "
b10101011 )
b0 $
b1010101011 #
#685
b1 $
b1010101100 #
#686
b10 $
b1010101101 #
#687
b11 $
b1010101110 #
#688
b10101100 "
b10101100 )
b0 $
b1010101111 #
#689
b1 $
b1010110000 #
#690
b10 $
b1010110001 #
#691
b11 $
b1010110010 #
#692
b10101101 "
b10101101 )
b0 $
b1010110011 #
#693
b1 $
b1010110100 #
#694
b10 $
b1010110101 #
#695
b11 $
b1010110110 #
#696
b10101110 "
b10101110 )
b0 $
b1010110111 #
#697
b1 $
b1010111000 #
#698
b10 $
b1010111001 #
#699
b11 $
b1010111010 #
#700
b10101111 "
b10101111 )
b0 $
b1010111011 #
#701
b1 $
b1010111100 #
#702
b10 $
b1010111101 #
#703
b11 $
b1010111110 #
#704
b10110000 "
b10110000 )
b0 $
b1010111111 #
#705
b1 $
b1011000000 #
#706
b10 $
b1011000001 #
#707
b11 $
b1011000010 #
#708
b10110001 "
b10110001 )
b0 $
b1011000011 #
#709
b1 $
b1011000100 #
#710
b10 $
b1011000101 #
#711
b11 $
b1011000110 #
#712
b10110010 "
b10110010 )
b0 $
b1011000111 #
#713
b1 $
b1011001000 #
#714
b10 $
b1011001001 #
#715
b11 $
b1011001010 #
#716
b10110011 "
b10110011 )
b0 $
b1011001011 #
#717
b1 $
b1011001100 #
#718
b10 $
b1011001101 #
#719
b11 $
b1011001110 #
#720
b10110100 "
b10110100 )
b0 $
b1011001111 #
#721
b1 $
b1011010000 #
#722
b10 $
b1011010001 #
#723
b11 $
b1011010010 #
#724
b10110101 "
b10110101 )
b0 $
b1011010011 #
#725
b1 $
b1011010100 #
#726
b10 $
b1011010101 #
#727
b11 $
b1011010110 #
#728
b10110110 "
b10110110 )
b0 $
b1011010111 #
#729
b1 $
b1011011000 #
#730
b10 $
b1011011001 #
#731
b11 $
b1011011010 #
#732
b10110111 "
b10110111 )
b0 $
b1011011011 #
#733
b1 $
b1011011100 #
#734
b10 $
b1011011101 #
#735
b11 $
b1011011110 #
#736
b10111000 "
b10111000 )
b0 $
b1011011111 #
#737
b1 $
b1011100000 #
#738
b10 $
b1011100001 #
#739
b11 $
b1011100010 #
#740
b10111001 "
b10111001 )
b0 $
b1011100011 #
#741
b1 $
b1011100100 #
#742
b10 $
b1011100101 #
#743
b11 $
b1011100110 #
#744
b10111010 "
b10111010 )
b0 $
b1011100111 #
#745
b1 $
b1011101000 #
#746
b10 $
b1011101001 #
#747
b11 $
b1011101010 #
#748
b10111011 "
b10111011 )
b0 $
b1011101011 #
#749
b1 $
b1011101100 #
#750
b10 $
b1011101101 #
#751
b11 $
b1011101110 #
#752
b10111100 "
b10111100 )
b0 $
b1011101111 #
#753
b1 $
b1011110000 #
#754
b10 $
b1011110001 #
